rxnpath/__init__.py
rxnpath/core.py
rxnpath/version.py
rxnpath-0.1.dist-info/LICENSE
rxnpath-0.1.dist-info/METADATA
rxnpath-0.1.dist-info/WHEEL
rxnpath-0.1.dist-info/top_level.txt
rxnpath-0.1.dist-info/RECORD
