Metadata-Version: 2.1
Name: rxnpath
Version: 0.1
Summary: rxnpath: a simple python package for generating reaction diagrams.
Home-page: http://github.com/ldgibson/rxnpath
Author: Luke D Gibson
Author-email: ldgibson@uw.edu
Maintainer: Luke D Gibson
Maintainer-email: ldgibson@uw.edu
License: MIT
Platform: OS Independent
Classifier: Development Status :: 3 - Alpha
Classifier: Environment :: Console
Classifier: Intended Audience :: Science/Research
Classifier: License :: OSI Approved :: MIT License
Classifier: Operating System :: OS Independent
Classifier: Programming Language :: Python
Classifier: Topic :: Scientific/Engineering
Requires-Dist: adjustText (>=0.7.3)
Requires-Dist: matplotlib (>=3.1.0)
Requires-Dist: networkx (>=2.3)
Requires-Dist: numpy (>=1.16.3)
